atlasapprox_disease/__init__.py
atlasapprox_disease/exceptions.py
atlasapprox_disease/utils.py
atlasapprox_disease-0.1.4.dist-info/LICENSE.txt
atlasapprox_disease-0.1.4.dist-info/METADATA
atlasapprox_disease-0.1.4.dist-info/WHEEL
atlasapprox_disease-0.1.4.dist-info/top_level.txt
atlasapprox_disease-0.1.4.dist-info/RECORD
