Metadata-Version: 2.2
Name: atlasapprox_disease
Version: 0.1.4
Summary: Cell atlas approximations for diseases, Python API
Author-email: Ying Xu <ying.xu3@unsw.edu.au>
License: Copyright 2025 Fabio Zanini
Project-URL: Repository, https://github.com/fabilab/cell_atlas_approximations_disease_API
Project-URL: Bug Tracker, https://github.com/fabilab/cell_atlas_approximations_disease_API/issues
Keywords: single cell,cell atlas,omics,biology,disease,bioinformatics
Classifier: Development Status :: 4 - Beta
Classifier: Intended Audience :: Developers
Classifier: Intended Audience :: Science/Research
Classifier: Programming Language :: Python :: 3
Classifier: Programming Language :: Python :: 3.7
Classifier: Programming Language :: Python :: 3.8
Classifier: Programming Language :: Python :: 3.9
Classifier: Programming Language :: Python :: 3.10
Classifier: Programming Language :: Python :: 3.11
Classifier: Programming Language :: Python :: 3.12
Classifier: Programming Language :: Python :: 3.13
Classifier: Programming Language :: Python :: 3 :: Only
Classifier: Topic :: Scientific/Engineering
Classifier: Topic :: Scientific/Engineering :: Bio-Informatics
Classifier: Topic :: Software Development :: Libraries :: Python Modules
Requires-Python: >=3.10
License-File: LICENSE.txt
Requires-Dist: requests
Requires-Dist: numpy
Requires-Dist: pandas
